psiaudio/__init__.py
psiaudio/buffer.py
psiaudio/calibration.py
psiaudio/efr.py
psiaudio/pipeline.py
psiaudio/plot.py
psiaudio/queue.py
psiaudio/stats.py
psiaudio/stim.py
psiaudio/testing.py
psiaudio/util.py
psiaudio/version.py
psiaudio/weighting.py
psiaudio/resources/__init__.py
psiaudio/resources/starship_cal.csv
psiaudio-0.4.3.dist-info/LICENSE.txt
psiaudio-0.4.3.dist-info/METADATA
psiaudio-0.4.3.dist-info/WHEEL
psiaudio-0.4.3.dist-info/top_level.txt
psiaudio-0.4.3.dist-info/RECORD
